bin/function3.sv
module top(
   input logic[12:0] sw,
   input logic btnr, A, B, C,
   output logic[15:0] led
);

assign led[15:3] = btnr ? 13'd0 : sw;
assign led[2:1] = btnr? 2'b00 : {C,B};
assign led[0] = btnr ? (A&~B)|(C) : A;

endmodule

vjvoshchjahgijh.vcd
$version Generated by VerilatedVcd $end
$date Fri Jul 15 21:05:31 2022
 $end
$timescale   1ns $end

 $scope module TOP $end
  $var wire  1 % A $end
  $var wire  1 & B $end
  $var wire  1 ' C $end
  $var wire  1 $ btnr $end
  $var wire 16 ( led [15:0] $end
  $var wire 13 # sw [12:0] $end
  $scope module top $end
   $var wire  1 % A $end
   $var wire  1 & B $end
   $var wire  1 ' C $end
   $var wire  1 $ btnr $end
   $var wire 16 ( led [15:0] $end
   $var wire 13 # sw [12:0] $end
  $upscope $end
 $upscope $end
$enddefinitions $end


#0
b0000000000000 #
0$
0%
0&
0'
b0000000000000000 (
#1
#2
#3
#4
#5
b1111111111111 #
1$
#6
1'
b0000000000000001 (
#7
1&
0'
b0000000000000000 (
#8
1'
b0000000000000001 (
#9
1%
0&
0'
#10
1'
#11
1&
0'
b0000000000000000 (
#12
1'
b0000000000000001 (
