bin/function4.sv
module top(
   input logic btnu, student, prof, pm,
   input logic[3:0] hour,
   input logic[8:0] sw,
   output logic[15:0] led
);

//Code Goes Here

endmodule

temp/xkxusbgeuzyfrii.vcd
$version Generated by VerilatedVcd $end
$date Tue Jul 26 20:37:45 2022
 $end
$timescale   1ns $end

 $scope module TOP $end
  $var wire  1 # btnu $end
  $var wire  4 ' hour [3:0] $end
  $var wire 16 ) led [15:0] $end
  $var wire  1 & pm $end
  $var wire  1 % prof $end
  $var wire  1 $ student $end
  $var wire  9 ( sw [8:0] $end
  $scope module top $end
   $var wire  1 # btnu $end
   $var wire  4 ' hour [3:0] $end
   $var wire 16 ) led [15:0] $end
   $var wire  1 & pm $end
   $var wire  1 % prof $end
   $var wire  1 $ student $end
   $var wire  9 ( sw [8:0] $end
  $upscope $end
 $upscope $end
$enddefinitions $end


#0
0#
0$
0%
0&
b0000 '
b111111111 (
b1111111110000000 )
#1
1%
b1011 '
b1111111111011010 )
#2
1#
b1111111111111111 )
#3
1&
#4
0&
b0010 '
#5
1&
#6
1$
0%
0&
b1011 '
b0000000000000000 )
#7
1&
#8
0&
b0010 '
#9
1&
#10
1%
0&
b1011 '
b1111111111111111 )
#11
0$
0%
b0000000000000000 )
#12
1$
1%
1&
b0001 '
b1111111111111111 )
